alu.v
// Inverter module
module invert(input wire [7:0] i, output wire [7:0] o);
   assign o = ~i;
endmodule

module and2 (input wire [7:0] i0, i1, output wire [7:0] o);
  assign o = i0 & i1;
endmodule

module xor2 (input wire [7:0] i0, i1, output wire [7:0] o);
  assign o = i0 ^ i1;
endmodule

module or2 (input wire [7:0] i0, i1, output wire [7:0] o);
  assign o = i0 | i1;
endmodule


module nand2 (input wire [7:0] i0, i1, output wire [7:0] o);
   wire [7:0] t;
   and2 and2_0 (.i0(i0), .i1(i1), .o(t));
   invert invert_0 (.i(t), .o(o));
endmodule

module lls (input wire [7:0] i0, output wire [7:0] o);
    assign o = i0 << 1;
endmodule

module lrs (input wire [7:0] i0, output wire [7:0] o);
    assign o = i0 >> 1;  
endmodule

// Full Adder module
module full_adder(
    output cout,
    output sum,
    input ain,
    input bin,
    input cin
    );

    //assign bin2 = cin^bin; // XORing the inputs to bin with cin. If 1, subtract; if 0, add
    
    assign sum = ain^bin^cin;
    assign cout = (ain&bin) | (ain&cin) | (bin&cin);
endmodule

module adder8(
    output cout, //MSB, determines if answer is positive or negative
    output [7:0] s,
    input [7:0] a,
    input [7:0] b,
    input cin // if 1, subtract, if 0, add. This is XOR'ed with b
    );
    
    wire [7:0] bin;
    assign bin[0] = b[0]^cin;
    assign bin[1] = b[1]^cin;
    assign bin[2] = b[2]^cin;
    assign bin[3] = b[3]^cin;
    assign bin[4] = b[4]^cin;                          
    assign bin[5] = b[5]^cin;
    assign bin[6] = b[6]^cin;
    assign bin[7] = b[7]^cin;
    
      
    wire [8:1] carry; 
     full_adder FA0(carry[1],s[0],a[0],bin[0],cin);
     full_adder FA1(carry[2],s[1],a[1],bin[1],carry[1]);
     full_adder FA2(carry[3],s[2],a[2],bin[2],carry[2]);
     full_adder FA3(carry[4],s[3],a[3],bin[3],carry[3]);
     full_adder FA4(carry[5],s[4],a[4],bin[4],carry[4]);
     full_adder FA5(carry[6],s[5],a[5],bin[5],carry[5]);
     full_adder FA6(carry[7],s[6],a[6],bin[6],carry[6]);
     full_adder FA7(carry[8],s[7],a[7],bin[7],carry[7]);
     
     assign cout = cin^carry[8];
   
endmodule

module alu(
  input wire [2:0] opcode,
  input wire [7:0] OperandA, OperandB,
  output reg [7:0] result
);

  wire [7:0] and_result, or_result, xor_result, nand_result, lls_result, lrs_result, negated_B, adder_sum, sub_sum;
  wire adder_cout, sub_cout;

  // Inverter for negating OperandB

  // Instantiate a full adder for addition
  adder8 adder_inst(.a(OperandA), .b(OperandB), .cin(1'b0), .s(adder_sum), .cout(adder_cout));
  adder8 sub_inst(.a(OperandA), .b(OperandB), .cin(1'b1), .s(sub_sum), .cout(sub_cout));
  and2 and_inst(.i0(OperandA), .i1(OperandB), .o(and_result));
  or2 or_inst(.i0(OperandA), .i1(OperandB), .o(or_result));
  xor2 xor_inst(.i0(OperandA), .i1(OperandB), .o(xor_result)); // Corrected instantiation for xor2
  nand2 nand_inst(.i0(OperandA), .i1(OperandB), .o(nand_result));
  lls lls_inst(.i0(OperandA), .o(lls_result));
  lrs lrs_inst(.i0(OperandA), .o(lrs_result));

  always @(*) begin
    case (opcode)
      3'b000: result = adder_sum[7:0];  // Output only the lower 8 bits for addition
      3'b001: result = sub_sum[7:0];  // Subtraction using full adder
      3'b010: result = lls_result; // Logical left shift
      3'b011: result = lrs_result; // Logical right shift
      3'b100: result = and_result; // AND
      3'b101: result = or_result; // OR
      3'b110: result = xor_result; // XOR
      3'b111: result = nand_result; // NAND
      default: result = 8'b0;
    endcase
  end

endmodule

tb_alu.v
// Testbench for ALU module
module alu_tb();
  reg [2:0] opcode;
  reg [7:0] OperandA, OperandB;
  wire [7:0] result;

  // Instantiate ALU module
  alu uut(
    .opcode(opcode),
    .OperandA(OperandA),
    .OperandB(OperandB),
    .result(result)
  );

  integer i;

  // Test cases
  initial begin 
    $dumpfile("dump.vcd");
    $dumpvars(0, alu_tb);
  end

  initial begin
    OperandA = 50; OperandB = 10; opcode = 3'b000;

    for (i = 1; i < 8; i = i + 1) begin
      #10
      opcode = i;
    end

    #10
    $finish();
  end

endmodule

dump.vcd
$date
	Fri Nov 24 09:48:17 2023
$end
$version
	Icarus Verilog
$end
$timescale
	1s
$end
$scope module alu_tb $end
$var wire 8 ! result [7:0] $end
$var reg 8 " OperandA [7:0] $end
$var reg 8 # OperandB [7:0] $end
$var reg 3 $ opcode [2:0] $end
$var integer 32 % i [31:0] $end
$scope module uut $end
$var wire 8 & OperandA [7:0] $end
$var wire 8 ' OperandB [7:0] $end
$var wire 3 ( opcode [2:0] $end
$var wire 8 ) xor_result [7:0] $end
$var wire 8 * sub_sum [7:0] $end
$var wire 1 + sub_cout $end
$var wire 8 , or_result [7:0] $end
$var wire 8 - nand_result [7:0] $end
$var wire 8 . lrs_result [7:0] $end
$var wire 8 / lls_result [7:0] $end
$var wire 8 0 and_result [7:0] $end
$var wire 8 1 adder_sum [7:0] $end
$var wire 1 2 adder_cout $end
$var reg 8 3 result [7:0] $end
$scope module adder_inst $end
$var wire 8 4 a [7:0] $end
$var wire 8 5 b [7:0] $end
$var wire 1 6 cin $end
$var wire 1 2 cout $end
$var wire 8 7 s [7:0] $end
$var wire 8 8 carry [8:1] $end
$var wire 8 9 bin [7:0] $end
$scope module FA0 $end
$var wire 1 : ain $end
$var wire 1 ; bin $end
$var wire 1 6 cin $end
$var wire 1 < cout $end
$var wire 1 = sum $end
$upscope $end
$scope module FA1 $end
$var wire 1 > ain $end
$var wire 1 ? bin $end
$var wire 1 @ cin $end
$var wire 1 A cout $end
$var wire 1 B sum $end
$upscope $end
$scope module FA2 $end
$var wire 1 C ain $end
$var wire 1 D bin $end
$var wire 1 E cin $end
$var wire 1 F cout $end
$var wire 1 G sum $end
$upscope $end
$scope module FA3 $end
$var wire 1 H ain $end
$var wire 1 I bin $end
$var wire 1 J cin $end
$var wire 1 K cout $end
$var wire 1 L sum $end
$upscope $end
$scope module FA4 $end
$var wire 1 M ain $end
$var wire 1 N bin $end
$var wire 1 O cin $end
$var wire 1 P cout $end
$var wire 1 Q sum $end
$upscope $end
$scope module FA5 $end
$var wire 1 R ain $end
$var wire 1 S bin $end
$var wire 1 T cin $end
$var wire 1 U cout $end
$var wire 1 V sum $end
$upscope $end
$scope module FA6 $end
$var wire 1 W ain $end
$var wire 1 X bin $end
$var wire 1 Y cin $end
$var wire 1 Z cout $end
$var wire 1 [ sum $end
$upscope $end
$scope module FA7 $end
$var wire 1 \ ain $end
$var wire 1 ] bin $end
$var wire 1 ^ cin $end
$var wire 1 _ cout $end
$var wire 1 ` sum $end
$upscope $end
$upscope $end
$scope module and_inst $end
$var wire 8 a i0 [7:0] $end
$var wire 8 b i1 [7:0] $end
$var wire 8 c o [7:0] $end
$upscope $end
$scope module lls_inst $end
$var wire 8 d i0 [7:0] $end
$var wire 8 e o [7:0] $end
$upscope $end
$scope module lrs_inst $end
$var wire 8 f i0 [7:0] $end
$var wire 8 g o [7:0] $end
$upscope $end
$scope module nand_inst $end
$var wire 8 h i0 [7:0] $end
$var wire 8 i i1 [7:0] $end
$var wire 8 j t [7:0] $end
$var wire 8 k o [7:0] $end
$scope module and2_0 $end
$var wire 8 l i0 [7:0] $end
$var wire 8 m i1 [7:0] $end
$var wire 8 n o [7:0] $end
$upscope $end
$scope module invert_0 $end
$var wire 8 o i [7:0] $end
$var wire 8 p o [7:0] $end
$upscope $end
$upscope $end
$scope module or_inst $end
$var wire 8 q i0 [7:0] $end
$var wire 8 r i1 [7:0] $end
$var wire 8 s o [7:0] $end
$upscope $end
$scope module sub_inst $end
$var wire 8 t a [7:0] $end
$var wire 8 u b [7:0] $end
$var wire 1 v cin $end
$var wire 1 + cout $end
$var wire 8 w s [7:0] $end
$var wire 8 x carry [8:1] $end
$var wire 8 y bin [7:0] $end
$scope module FA0 $end
$var wire 1 z ain $end
$var wire 1 { bin $end
$var wire 1 v cin $end
$var wire 1 | cout $end
$var wire 1 } sum $end
$upscope $end
$scope module FA1 $end
$var wire 1 ~ ain $end
$var wire 1 !" bin $end
$var wire 1 "" cin $end
$var wire 1 #" cout $end
$var wire 1 $" sum $end
$upscope $end
$scope module FA2 $end
$var wire 1 %" ain $end
$var wire 1 &" bin $end
$var wire 1 '" cin $end
$var wire 1 (" cout $end
$var wire 1 )" sum $end
$upscope $end
$scope module FA3 $end
$var wire 1 *" ain $end
$var wire 1 +" bin $end
$var wire 1 ," cin $end
$var wire 1 -" cout $end
$var wire 1 ." sum $end
$upscope $end
$scope module FA4 $end
$var wire 1 /" ain $end
$var wire 1 0" bin $end
$var wire 1 1" cin $end
$var wire 1 2" cout $end
$var wire 1 3" sum $end
$upscope $end
$scope module FA5 $end
$var wire 1 4" ain $end
$var wire 1 5" bin $end
$var wire 1 6" cin $end
$var wire 1 7" cout $end
$var wire 1 8" sum $end
$upscope $end
$scope module FA6 $end
$var wire 1 9" ain $end
$var wire 1 :" bin $end
$var wire 1 ;" cin $end
$var wire 1 <" cout $end
$var wire 1 =" sum $end
$upscope $end
$scope module FA7 $end
$var wire 1 >" ain $end
$var wire 1 ?" bin $end
$var wire 1 @" cin $end
$var wire 1 A" cout $end
$var wire 1 B" sum $end
$upscope $end
$upscope $end
$scope module xor_inst $end
$var wire 8 C" i0 [7:0] $end
$var wire 8 D" i1 [7:0] $end
$var wire 8 E" o [7:0] $end
$upscope $end
$upscope $end
$upscope $end
$enddefinitions $end
$comment Show the parameter values. $end
$dumpall
$end
#0
$dumpvars
b111000 E"
b1010 D"
b110010 C"
0B"
1A"
1@"
1?"
0>"
0="
1<"
1;"
1:"
09"
18"
17"
16"
15"
14"
03"
12"
01"
10"
1/"
1."
0-"
1,"
0+"
0*"
0)"
1("
1'"
1&"
0%"
0$"
1#"
1""
0!"
1~
0}
1|
1{
0z
b11110101 y
b11110111 x
b101000 w
1v
b1010 u
b110010 t
b111010 s
b1010 r
b110010 q
b11111101 p
b10 o
b10 n
b1010 m
b110010 l
b11111101 k
b10 j
b1010 i
b110010 h
b11001 g
b110010 f
b1100100 e
b110010 d
b10 c
b1010 b
b110010 a
0`
0_
0^
0]
0\
0[
0Z
0Y
0X
0W
1V
0U
0T
0S
1R
1Q
0P
0O
0N
1M
1L
0K
0J
1I
0H
1G
0F
1E
0D
0C
0B
1A
0@
1?
1>
0=
0<
0;
0:
b1010 9
b10 8
b111100 7
06
b1010 5
b110010 4
b111100 3
02
b111100 1
b10 0
b1100100 /
b11001 .
b11111101 -
b111010 ,
0+
b101000 *
b111000 )
b0 (
b1010 '
b110010 &
b1 %
b0 $
b1010 #
b110010 "
b111100 !
$end
#10
b101000 !
b101000 3
b10 %
b1 $
b1 (
#20
b1100100 !
b1100100 3
b11 %
b10 $
b10 (
#30
b11001 !
b11001 3
b100 %
b11 $
b11 (
#40
b10 !
b10 3
b101 %
b100 $
b100 (
#50
b111010 !
b111010 3
b110 %
b101 $
b101 (
#60
b111000 !
b111000 3
b111 %
b110 $
b110 (
#70
b11111101 !
b11111101 3
b1000 %
b111 $
b111 (
